ml_lstm/__init__.py
ml_lstm/text_reader.py
ml_lstm/data/my_code.py
ml_lstm-0.1.dist-info/METADATA
ml_lstm-0.1.dist-info/WHEEL
ml_lstm-0.1.dist-info/top_level.txt
ml_lstm-0.1.dist-info/RECORD
