Metadata-Version: 2.1
Name: ml-lstm
Version: 0.1
Summary: Code for LSTM on IMDb Dataset
Home-page: https://github.com/savioratharv/prac_testing
Author: davinci003
Author-email: freegpt00@gmail.com
